odoo/addons/account_invoice_qr_code_sepa_payconiq/README.rst
odoo/addons/account_invoice_qr_code_sepa_payconiq/__init__.py
odoo/addons/account_invoice_qr_code_sepa_payconiq/__manifest__.py
odoo/addons/account_invoice_qr_code_sepa_payconiq/i18n/account_invoice_qr_code_sepa_payconiq.pot
odoo/addons/account_invoice_qr_code_sepa_payconiq/i18n/it.po
odoo/addons/account_invoice_qr_code_sepa_payconiq/models/__init__.py
odoo/addons/account_invoice_qr_code_sepa_payconiq/models/res_company.py
odoo/addons/account_invoice_qr_code_sepa_payconiq/models/res_config_settings.py
odoo/addons/account_invoice_qr_code_sepa_payconiq/models/res_partner_bank.py
odoo/addons/account_invoice_qr_code_sepa_payconiq/readme/CONFIGURE.rst
odoo/addons/account_invoice_qr_code_sepa_payconiq/readme/CONTRIBUTORS.rst
odoo/addons/account_invoice_qr_code_sepa_payconiq/readme/DESCRIPTION.rst
odoo/addons/account_invoice_qr_code_sepa_payconiq/readme/ROADMAP.rst
odoo/addons/account_invoice_qr_code_sepa_payconiq/readme/USAGE.rst
odoo/addons/account_invoice_qr_code_sepa_payconiq/static/description/icon.png
odoo/addons/account_invoice_qr_code_sepa_payconiq/static/description/index.html
odoo/addons/account_invoice_qr_code_sepa_payconiq/tests/__init__.py
odoo/addons/account_invoice_qr_code_sepa_payconiq/tests/test_payconiq_qr.py
odoo/addons/account_invoice_qr_code_sepa_payconiq/views/res_config_settings.xml
odoo14_addon_account_invoice_qr_code_sepa_payconiq-14.0.1.0.1.dev4.dist-info/METADATA
odoo14_addon_account_invoice_qr_code_sepa_payconiq-14.0.1.0.1.dev4.dist-info/WHEEL
odoo14_addon_account_invoice_qr_code_sepa_payconiq-14.0.1.0.1.dev4.dist-info/top_level.txt
odoo14_addon_account_invoice_qr_code_sepa_payconiq-14.0.1.0.1.dev4.dist-info/RECORD
